{"authors":[{"email":"aalmiray@users.sourceforge.net","name":"Andres Almiray"}],"title":"CSS for Swing","toolkits":["swing"],"source":"http://svn.codehaus.org/griffon/plugins/griffon-css-builder","releases":[{"version":"0.9","griffonVersion":"0.9.5 > *","dependencies":[],"type":"plugin","checksum":"75b1e07882f7cb8ad3377356d25b5f80","date":"2012-02-14T18:18:18+0100"},{"griffonVersion":"0.9.3 > *","dependencies":[],"checksum":"253dd18c095135905364732ae43ea9c0","type":"plugin","date":"2011-05-17T07:06:10+0200","version":"0.8"},{"griffonVersion":"0.9.2 > *","dependencies":[],"checksum":"46f3aaa6190ff442c67d08530f5b4f4e","type":"plugin","date":"2011-02-22T21:31:07+0100","version":"0.7"},{"griffonVersion":"0.9 > *","dependencies":[],"checksum":"38b89c3b65c3ff387025c9f97747fd1e","type":"plugin","date":"2010-07-21T16:59:24+0200","version":"0.6"},{"griffonVersion":"0.3 > *","dependencies":[],"checksum":"0588e7ec2468c7b73eb4e10bb2195fa3","type":"plugin","date":"2010-04-13T10:05:29+0200","version":"0.5"},{"griffonVersion":"0.3 < *","dependencies":[],"checksum":"e272ac1fd89b7b1d858a1265769d0d6e","type":"plugin","date":"2010-04-13T10:05:14+0200","version":"0.4"},{"griffonVersion":"0.3 < *","dependencies":[],"checksum":"3263c6573bb5b8c5197347a90a48def4","type":"plugin","date":"2010-04-13T10:04:57+0200","version":"0.3"},{"griffonVersion":"0.3 < *","dependencies":[],"checksum":"dedc38e3fb75e67753cfba0729f5942e","type":"plugin","date":"2010-04-13T10:04:48+0200","version":"0.2"},{"griffonVersion":"0.3 < *","dependencies":[],"checksum":"cd1e81a8f02ddc759433edf9caff143e","type":"plugin","date":"2010-04-13T10:04:35+0200","version":"0.1"}],"description":"Enables styling a Griffon application with CSS","name":"css-builder","platforms":[],"license":"Apache Software License 2.0"}