{"name":"gparallelizer","title":"GParallelizer Plugin","description":"","license":"<UNKNOWN>","source":"http://svn.codehaus.org/griffon/plugins/griffon-gparallelizer","authors":[{"name":"Vaclav Pech","email":""}],"toolkits":[],"platforms":[],"releases":[{"version":"0.3","griffonVersion":"0.3 < *","dependencies":[],"date":"2010-04-12T17:25:35+0200","type":"plugin","checksum":"d42c027adf5f7b612885eafb512d69ae"},{"version":"0.2","griffonVersion":"0.3 < *","dependencies":[],"date":"2010-04-12T17:23:24+0200","type":"plugin","checksum":"01b01497f69ece58feec8988c774bf77"},{"version":"0.1","griffonVersion":"0.3 < *","dependencies":[],"date":"2010-04-12T17:22:07+0200","type":"plugin","checksum":"935188c732e84beee5c31fec9833b206"}]}