{"name":"lookandfeel","title":"Swing Look & Feel selector","description":"Swing Look & Feel selector.","license":"Apache Software License 2.0","source":"http://svn.codehaus.org/griffon/plugins/griffon-lookandfeel","authors":[{"name":"Andres Almiray","email":"aalmiray@users.sourceforge.net"}],"toolkits":["swing"],"platforms":[],"releases":[{"version":"0.5","griffonVersion":"0.9.3 > *","dependencies":[{"name":"miglayout","version":"0.2"}],"date":"2011-06-25T22:20:09+0200","checksum":"5e588584b3c355c63059406a3d7fdfe1"},{"version":"0.4","griffonVersion":"0.9.2 > *","dependencies":[{"name":"miglayout","version":"0.2"}],"date":"2011-02-22T21:31:32+0100","checksum":"0036d57209cd9986c4f76f0c1553f5a5"},{"version":"0.3","griffonVersion":"0.9.1 > *","dependencies":[{"name":"miglayout","version":"0.1"}],"date":"2010-10-27T19:52:39+0200","checksum":"b4d8059472d7596a18028be6244adbaa"},{"version":"0.2","griffonVersion":"0.9 > *","dependencies":[{"name":"miglayout","version":"0.1"}],"date":"2010-08-18T19:19:38+0200","checksum":"2ddb5b705b3bee1b0e97b609e3ad8597"},{"version":"0.1","griffonVersion":"0.9 > *","dependencies":[{"name":"miglayout","version":"0.1"}],"date":"2010-07-21T09:33:31+0200","checksum":"f093ae1903d0320f30c8defccf8cc647"}]}