{"name":"quartz","title":"Job scheduling via Quartz","description":"Job scheduling via Quartz.\nBased on the Grails plugin of the same name.","license":"Apache Software License 2.0","source":"http://svn.codehaus.org/griffon/plugins/griffon-quartz","authors":[{"name":"Andres Almiray","email":"aalmiray@users.sourceforge.net"}],"toolkits":[],"platforms":[],"version":"0.1","griffonVersion":"0.9.2 > *","dependencies":[{"name":"spring","version":"0.5"}],"date":"2011-01-03T11:06:32+0100","type":"plugin"}